tentacule/__init__.py
tentacule/i_process_pool.py
tentacule/i_worker_process.py
tentacule/process_pool.py
tentacule/result_event.py
tentacule/utils.py
tentacule/worker_process.py
tentacule-0.1.8.dist-info/LICENSE
tentacule-0.1.8.dist-info/METADATA
tentacule-0.1.8.dist-info/WHEEL
tentacule-0.1.8.dist-info/top_level.txt
tentacule-0.1.8.dist-info/RECORD
