Metadata-Version: 2.1
Name: tentacule
Version: 0.1.8
Summary: "Tentacule is an uncomplicated library to deal with a pool of worker processes"
Author: "Charles Smith"
Author-email: "binarskugga@gmail.com"
License: "MIT"
License-File: LICENSE
Requires-Dist: dill ==0.3.*
